LICENSE
PY-LIC
setup.py
lmtpd/__init__.py
lmtpd/tests.py
lmtpd.egg-info/PKG-INFO
lmtpd.egg-info/SOURCES.txt
lmtpd.egg-info/dependency_links.txt
lmtpd.egg-info/top_level.txt